Metadata-Version: 2.4
Name: apax
Version: 0.12.3
Summary: Atomistic Learned Potential Package in JAX
Project-URL: Repository, https://github.com/apax-hub/apax
Project-URL: Releases, https://github.com/apax-hub/apax/releases
Project-URL: Discord, https://discord.gg/7ncfwhsnm4
Project-URL: Documentation, https://apax.readthedocs.io/
Author-email: Moritz René Schäfer <schaefer@theochem.uni-stuttgart.de>, Nico Segreto <segreto@theochem.uni-stuttgart.de>
License-Expression: MIT
License-File: LICENSE
Keywords: interatomic potentials,machine-learning,molecular-dynamics
Requires-Python: >=3.10
Requires-Dist: ase>=3.24.0
Requires-Dist: clu>=0.0.12
Requires-Dist: e3x>=1.0.2
Requires-Dist: einops>=0.8.0
Requires-Dist: flax>=0.10.6
Requires-Dist: jax==0.6.2
Requires-Dist: lazy-loader>=0.4
Requires-Dist: numpy>=1.23
Requires-Dist: optax>=0.2.4
Requires-Dist: orbax-checkpoint>=0.11.0
Requires-Dist: pydantic>=2.10.5
Requires-Dist: tensorflow>=2.12.0
Requires-Dist: typer>=0.13.0
Requires-Dist: uncertainty-toolbox>=0.1.1
Requires-Dist: vesin>=0.3.0
Requires-Dist: znh5md>=0.4.5
Provides-Extra: cuda
Requires-Dist: jax[cuda]; extra == 'cuda'
Provides-Extra: docs
Requires-Dist: furo>=2023.9.10; extra == 'docs'
Requires-Dist: ipykernel>=6.29.3; extra == 'docs'
Requires-Dist: myst-parser>=2.0.0; extra == 'docs'
Requires-Dist: nbsphinx-link>=1.3.0; extra == 'docs'
Requires-Dist: nbsphinx>=0.9.3; extra == 'docs'
Requires-Dist: pandoc>=2.3; extra == 'docs'
Requires-Dist: sphinx-copybutton>=0.5.2; extra == 'docs'
Requires-Dist: sphinx-rtd-theme>=1.3.0; extra == 'docs'
Requires-Dist: sphinx>=7.2.6; extra == 'docs'
Provides-Extra: ipsuite
Requires-Dist: ipsuite>=0.2.3; extra == 'ipsuite'
Provides-Extra: mlflow
Requires-Dist: mlflow>=2.19.0; extra == 'mlflow'
